{
  "indo": [
    { "id": 1, "title": "", "yyy": "", "iklan": "", "url": "", "imgurl": "" },
    { "id": 2, "title": "", "yyy": "", "iklan": "", "url": "" },
    { "id": 3, "title": "", "yyy": "", "iklan": "", "url": "" },
    { "id": 4, "title": "", "yyy": "", "iklan": "", "url": "" },
    { "id": 5, "title": "", "yyy": "", "iklan": "", "url": "" },
    { "id": 6, "title": "", "yyy": "", "iklan": "", "url": "" },
    { "id": 7, "title": "", "yyy": "", "iklan": "", "url": "" },
    { "id": 8, "title": "", "yyy": "", "iklan": "", "url": "" },
    { "id": 9, "title": "", "yyy": "", "iklan": "", "url": "" },
    { "id": 10, "title": "", "yyy": "", "iklan": "", "url": "" },
    { "id": 11, "title": "", "yyy": "", "iklan": "", "url": "" },
    { "id": 12, "title": "", "yyy": "", "iklan": "", "url": "" },
    { "id": 13, "title": "", "yyy": "", "iklan": "", "url": "" },
    { "id": 14, "title": "", "yyy": "", "iklan": "", "url": "" },
    { "id": 15, "title": "", "yyy": "", "iklan": "", "url": "" },
    { "id": 16, "title": "", "yyy": "", "iklan": "", "url": "" }
  ],
  "comments": [
    { "id": 1, "body": "some comment", "postId": 1 },
    { "id": 2, "body": "some comment", "postId": 1 }
  ],
  "profile": {
    "name": "typicode"
  }
}
